{
  "celestial": {
      "weight": 5,
      "sets": [
          {
              "species": "Celestial",
              "weight": 20,
              "moves": [
                  ["Laser Delusion"],
                  ["Calm Mind","Nasty Plot"],
                  ["Aura Sphere"],
                  ["Heal Order","Roost"]
              ],
              "item": ["Life Orb","Leftovers"],
              "nature": "Modest",
              "evs": {"hp": 248, "spa": 252, "spd": 8},
              "teraType": ["Normal"],
              "ability": ["Orgueil Celeste"]
          },
          {
              "species": "Celestial",
              "weight": 20,
              "moves": [
                  ["Laser Delusion"],
                  ["Calm Mind","Nasty Plot"],
                  ["Defog"],
                  ["Heal Order","Roost"]
              ],
              "item": ["Heavy-Duty Boots"],
              "nature": "Bold",
              "evs": {"hp": 248, "spa": 252, "spd": 8},
              "teraType": ["Normal"],
              "ability": ["Orgueil Celeste"]
          },
          {
              "species": "Celestial",
              "weight": 20,
              "moves": [
                  ["Laser Delusion"],
                  ["Glitzy Glow"],
                  ["U-Turn"],
                  ["Heal Order","Roost"]
              ],
              "item": ["Light Clay"],
              "nature": "Bold",
              "evs": {"hp": 248, "spa": 252, "spd": 8},
              "teraType": ["Normal"],
              "ability": ["Orgueil Celeste"]
          },
          {
              "species": "Celestial",
              "weight": 20,
              "moves": [
                  ["Laser Delusion"],
                  ["Wish"],
                  ["Protect"],
                  ["Heal Bell","Thunder Wave"]
              ],
              "item": ["Leftovers"],
              "nature": "Calm",
              "evs": {"hp": 252, "spd": 252, "spa": 84},
             "teraType": ["Normal"],
              "ability": ["Orgueil Celeste"]
          },
          {
              "species": "Celestial",
              "weight": 20,
              "moves": [
                  ["Laser Delusion"],
                  ["Draco Meteor","Dragon Pulse"],
                  ["Heat Wave","Aura Sphere"],
                  ["U-Turn"]
              ],
              "item": ["Leftovers"],
              "nature": "Timid",
              "evs": {"spa": 252, "spe": 252, "spd": 4},
              "teraType": ["Normal"],
              "ability": ["Orgueil Celeste"]
          }
      ]
  },
  "gardilisk": {
      "weight": 10,
      "sets": [
          {
              "species": "Gardilisk",
              "weight": 20,
              "moves": [
                  ["Dragon Blade"],
                  ["Outrage","Dragon Claw","Dragon Tail"],
                  ["Sacred Sword", "Brick Break"],
                  ["Quick Slice"]
              ],
              "item": ["Assault Vest","Life Orb","Leftovers","Rocky Helmet","Choice Scarf","Choice Band"],
              "nature": "Adamant",
              "evs": {"hp": 248, "atk": 252, "spd": 8},
              "teraType": ["Normal"],
              "ability": ["Sharpness","Hyper Cutter"]
          },
          {
              "species": "Gardilisk",
              "weight": 20,
              "moves": [
                  ["Dragon Blade"],
                  ["Dragon Claw","Outrage"],
                  ["Sacred Sword", "Brick Break"],
                  ["Autotomize","Swords Dance","Quick Slice"]
              ],
              "item": ["Life Orb","Leftovers","Rocky Helmet"],
              "nature": "Adamant",
              "evs": {"atk": 248, "spe": 252, "def": 8},
              "teraType": ["Normal"],
              "ability": ["Sharpness","Hyper Cutter"]
          },
          {
              "species": "Gardilisk",
              "weight": 20,
              "moves": [
                  ["Dragon Blade"],
                  ["Substitute"],
                  ["Sacred Sword"],
                  ["Swords Dance"]
              ],
              "item": ["Salac Berry"],
              "nature": "Jolly",
              "evs": {"atk": 248, "spe": 252, "def": 8},
              "teraType": ["Normal"],
              "ability": ["Sharpness","Hyper Cutter"]
          }
      ]
  },
  "cockalypse": {
      "weight": 50,
      "sets": [
          {
              "species": "Cockalypse",
              "weight": 20,
              "moves": [
                  ["Bolt Beak"],
                  ["Outrage", "Dragon Claw"],
                  ["Earthquake","Superpower"],
                  ["Volt Switch"]
              ],
              "item": ["Choice Scarf"],
              "nature": "Jolly",
              "evs": {"atk": 252, "spe": 252, "spa": 4},
              "teraType": ["Fairy", "Water"],
              "ability": ["Mold Breaker"]
          },
          {
              "species": "Cockalypse",
              "weight": 20,
              "moves": [
                  ["Thunder","Thunderbolt"],
                  ["Draco Meteor","Dragon Pulse"],
                  ["Heat Wave"],
                  ["Volt Switch"]
              ],
              "item": ["Choice Scarf"],
              "nature": "Timid",
              "evs": {"spa": 252, "spe": 252, "def": 4},
              "teraType": ["Fairy", "Water"],
              "ability": ["Mold Breaker"]
          },
          {
              "species": "Cockalypse",
              "weight": 20,
              "moves": [
                  ["Tailwind","Thunder Wave"],
                  ["Dragon Tail","Dragon Pulse"],
                  ["Roost"],
                  ["Volt Switch"]
              ],
              "item": ["Leftovers","Heavy-Duty Boots"],
              "nature": "Rash",
              "evs": {"hp": 248, "spa": 252, "spd": 8},
              "teraType": ["Fairy", "Water"],
              "ability": ["Mold Breaker"]
          }
      ]
  },
  "puyotan": {
      "weight": 50,
      "sets": [
          {
              "species": "Puyotan",
              "weight": 20,
              "moves": [
                  ["Outrage"],
                  ["Knock Off"],
                  ["U-Turn"],
                  ["Dragon Tail"]
              ],
              "item": ["Choice Scarf"],
              "nature": "Jolly",
              "evs": {"hp": 252, "spd": 4, "spe": 252},
              "teraType": ["Grass", "Poison", "Water"],
              "ability": ["Imposter"]
          },
          {
              "species": "Puyotan",
                "weight": 1,
                "moves": [
                    ["Pain Split"],
                    ["Dragon Tail", "Haze"],
                    ["Knock Off", "Encore"],
                    ["U-turn" ]
                ],
                "item": ["Flame Orb"],
                "nature": "Impish",
                "evs": {"def": 252, "hp": 252 , "spd": 4 },
                "teraType": ["Steel"],
                "ability": ["Marvel Scale"]
          },
          {
               "species": "Puyotan",
                "weight": 1,
                "moves": [
                    ["Imprison"],
                    ["Transform"],
                    ["Whirlpool"],
                    ["U-turn" ]
                ],
                "item": ["Sitrus Berry", "Leftovers", "Red Card"],
                "nature": "Jolly",
                "evs": {"spe": 252, "def": 252 , "spd": 4 },
                "teraType": ["Steel"],
                "ability": ["Marvel Scale", "Berserk"]
          }
      ]
  },
  "terrakami": {
      "weight": 50,
      "sets": [
          {
              "species": "Terrakami",
              "weight": 20,
              "moves": [
                  ["Stealth Rock"],
                  ["U-Turn"],
                  ["Earthquake","Land's Wrath"],
                  ["Dragon Tail","Rapid Spin"]
              ],
              "item": ["Rocky Helmet","Leftovers"],
              "nature": "Adamant",
              "evs": {"hp": 252, "spd": 4, "atk": 252},
              "teraType": ["Grass", "Poison", "Water"],
              "ability": ["Earth Eater"]
          },
          {
              "species": "Terrakami",
              "weight": 20,
              "moves": [
                  ["Coil"],
                  ["Recover"],
                  ["Earthquake","Land's Wrath"],
                  ["Rapid Spin"]
              ],
              "item": ["Leftovers","Life Orb"],
              "nature": "Careful",
              "evs": {"hp": 252, "spd": 252, "atk": 4},
              "teraType": ["Grass", "Poison", "Water"],
              "ability": ["Earth Eater"]
          },
          {
              "species": "Terrakami",
              "weight": 20,
              "moves": [
                  ["Nature's Madness"],
                  ["U-Turn"],
                  ["Earthquake","Land's Wrath"],
                  ["Rapid Spin"]
              ],
              "item": ["Leftovers","Heavy-Duty Boots"],
              "nature": "Careful",
              "evs": {"hp": 252, "spd": 252, "atk": 4},
              "teraType": ["Grass", "Poison", "Water"],
              "ability": ["Earth Eater"]
          },
          {
              "species": "Terrakami",
              "weight": 20,
              "moves": [
                  ["Dragon Tail"],
                  ["Stealth Rock"],
                  ["Earthquake","Land's Wrath"],
                  ["Spikes"]
              ],
              "item": ["Rocky Helmet"],
              "nature": "Adamant",
              "evs": {"hp": 248, "spd": 252, "def": 8},
              "teraType": ["Grass", "Poison", "Water"],
              "ability": ["Earth Eater"]
          },
          {
              "species": "Terrakami",
              "weight": 20,
              "moves": [
                  ["Outrage","Dragon Claw"],
                  ["U-Turn"],
                  ["Earthquake","Land's Wrath"],
                  ["Fire Fang"]
              ],
              "item": ["Choice Band"],
              "nature": "Jolly",
              "evs": {"atk": 252, "spe": 252, "def": 4},
              "teraType": ["Grass", "Poison", "Water"],
              "ability": ["Earth Eater"]
          }
      ]
  },
  "glaugoon": {
      "weight": 70,
      "sets": [
          {
              "species": "Glaugoon",
              "weight": 20,
              "moves": [
                  ["Drache Toxic"],
                  ["Sludge Wave","Draco Meteor"],
                  ["Reflect","Light Screen"],
                  ["Flip Turn"]
              ],
              "item": ["Light Clay"],
              "nature": "Timid",
              "evs": {"spa": 252, "spe": 252, "def": 4},
              "teraType": ["Fairy", "Grass"],
              "ability": ["Gooey"]
          },
          {
              "species": "Glaugoon",
              "weight": 20,
              "moves": [
                  ["Drache Toxic","Sludge Wave"],
                  ["Focus Blast"],
                  ["Reflect","Light Screen"],
                  ["Flip Turn"]
              ],
              "item": ["Focus Sash"],
              "nature": "Timid",
              "evs": {"spa": 252, "spe": 252, "def": 4},
              "teraType": ["Fairy", "Grass"],
              "ability": ["Gooey"]
          },
          {
              "species": "Glaugoon",
              "weight": 20,
              "moves": [
                  ["Drache Toxic"],
                  ["Sludge Wave","Focus Blast","Ice Beam"],
                  ["Dragon Pulse","Draco Meteor"],
                  ["Flip Turn"]
              ],
              "item": ["Choice Scarf","Choice Specs"],
              "nature": "Timid",
              "evs": {"spa": 252, "spe": 252, "def": 4},
              "teraType": ["Fairy", "Grass"],
              "ability": ["Gooey","Poison Point"]
          },
          {
              "species": "Glaugoon",
              "weight": 20,
              "moves": [
                  ["agility"],
                  ["Sludge Wave","Sludge Bomb"],
                  ["Dragon Pulse","Draco Meteor"],
                  ["Focus Blast"]
              ],
              "item": ["Life Orb","Expert Belt"],
              "nature": "Timid",
              "evs": {"spa": 252, "spe": 252, "def": 4},
              "teraType": ["Fairy", "Grass"],
              "ability": ["Gooey","Poison Point"]
          }
      ]
  },

  "gyaoon": {
      "weight": 70,
      "sets": [
        {
            "species": "Gyaoon",
            "weight": 20,
            "moves": [
                ["Belly Drum"],
                ["Body Slam"],
                ["Earthquake","Dragon Claw"],
                ["Knock Off"]
            ],
            "item": ["Leftovers","Sitrus Berry"],
            "nature": "Adamant",
            "evs": {"hp": 252, "atk": 252, "spd": 4},
            "teraType": ["Fairy", "Ghost"],
            "ability": ["Unaware"]
        },
        {
            "species": "Gyaoon",
            "weight": 20,
            "moves": [
                ["Shed Tail"],
                ["Body Slam"],
                ["Slack Off","Dragon Claw"],
                ["Knock Off","Thunder Wave"]
            ],
            "item": ["Leftovers","Sitrus Berry"],
            "nature": "Carfeul",
            "evs": {"hp": 252, "spd": 252, "atk": 4},
            "teraType": ["Fairy", "Ghost"],
            "ability": ["Unaware"]
        },
        {
            "species": "Gyaoon",
            "weight": 20,
            "moves": [
                ["Dragon Dance"],
                ["Body Slam"],
                ["Earthquake","Dragon Claw"],
                ["Knock Off","Thunder Wave","Slack Off"]
            ],
            "item": ["Sitrus Berry"],
            "nature": "Adamant",
            "evs": {"atk": 252, "spe": 252, "def": 4},
            "teraType": ["Fairy", "Ghost"],
            "ability": ["Unaware"]
        }
      ]
  },
    "invocamon": {
      "weight": 50,
      "sets": [
        {
            "species": "Invocamon",
            "weight": 20,
            "moves": [
                ["Dragon Rush,","Draco Meteor"],
                ["Dual Wingbeat","Aeroblast"],
                ["Blizzard","Thunder"],
                ["Fire Blast","Earthquake"]
            ],
            "item": ["Life Orb","Expert Belt","Choice Scarf"],
            "nature": "Timid",
            "evs": {"atk": 4 , "spa": 252 , "spe": 252 },
            "teraType": ["Fairy"],
            "ability": ["No Guard"]
        },
        {
            "species": "Invocamon",
            "weight": 20,
            "moves": [
                ["Dragon Rush"],
                ["Dual Wingbeat"],
                ["Iron Head"],
                ["Earthquake"]
            ],
            "item": ["Life Orb","Expert Belt","Choice Scarf","Choice Band"],
            "nature": "Jolly",
            "evs": {"spa": 4 , "atk": 252 , "spe": 252 },
            "teraType": ["Fairy"],
            "ability": ["No Guard"]
        },
        {
            "species": "Invocamon",
            "weight": 20,
            "moves": [
                ["Dragon Rush","Draco Meteor"],
                ["Aeroblast"],
                ["Earthquake"],
                ["Fire Blast","Iron Head"]
            ],
            "item": ["Life Orb","Expert Belt","Lum Berry"],
            "nature": "Timid",
            "evs": {"atk": 4 , "spa": 252 , "spe": 252 },
            "teraType": ["Fairy"],
            "ability": ["No Guard"]
        },
        {
            "species": "Invocamon",
            "weight": 20,
            "moves": [
                ["Dragon Rush"],
                ["Dragon Dance"],
                ["Iron Head"],
                ["Earthquake"]
            ],
            "item": ["Life Orb","Expert Belt","Heavy-Duty Boots"],
            "nature": "Jolly",
            "evs": {"spa": 4 , "atk": 252 , "spe": 252 },
            "teraType": ["Fairy"],
            "ability": ["No Guard"]
        },
        {
            "species": "Invocamon",
            "weight": 20,
            "moves": [
                ["Dragon Rush"],
                ["Dragon Dance"],
                ["Iron Head"],
                ["Sky Attack"]
            ],
            "item": ["Power Herb"],
            "nature": "Adament",
            "evs": {"spa": 4 , "atk": 252 , "spe": 252 },
            "teraType": ["Fairy"],
            "ability": ["No Guard"]
        }
      ]
    },
    "melodrame": {
      "weight": 50,
      "sets": [
        {
            "species": "Melodrame",
            "weight": 20,
            "moves": [
                ["Boomburst"],
                ["Dark Pulse", "Alluring Voice"],
                ["Encore"],
                ["Destiny Bond","Parting Shot"]
            ],
            "item": ["Life Orb","Focus Sash"],
            "nature": "Timid",
            "evs": {"spa": 252 , "spe": 252, "spd": 4},
            "teraType": ["Normal"],
            "ability": ["Punk Rock"]
        },
        {
            "species": "Melodrame",
            "weight": 5,
            "moves": [
                ["Boomburst"],
                ["Dark Pulse","Snarl"],
                ["Focus Energy"],
                ["Overdrive", "Alluring Voice"]
            ],
            "item": ["Leek"],
            "nature": "Timid",
            "evs": {"spa": 252 , "spe": 252, "spd": 4},
            "teraType": ["Normal"],
            "ability": ["Punk Rock"]
        },
        {
            "species": "Melodrame",
            "weight": 10,
            "moves": [
                ["Boomburst"],
                ["Dark Pulse", "Alluring Voice"],
                ["Switcheroo"],
                ["Healing Wish"]
            ],
            "item": ["Choice Scarf"],
            "nature": "Timid",
            "evs": {"spa": 252 , "spe": 252, "spd": 4},
            "teraType": ["Normal"],
            "ability": ["Punk Rock"]
        },
        {
            "species": "Melodrame",
            "weight": 10,
            "moves": [
                ["Boomburst"],
                ["Snarl", "Dark Pulse"],
                ["Alluring Voice"],
                ["Parting Shot"]
            ],
            "item": ["Choice Scarf"],
            "nature": "Timid",
            "evs": {"spa": 252 , "spe": 252, "spd": 4},
            "teraType": ["Normal"],
            "ability": ["Punk Rock"]
        }
      ]
    },
    "mandelman": {
      "weight": 50,
      "sets": [
        {
            "species": "Mandelman",
            "weight": 20,
            "moves": [
                ["Nasty Plot"],
                ["Destiny Bond"],
                ["Disable","Parting Shot"],
                ["Baddy Bad"]
            ],
            "item": ["Light Clay"],
            "nature": "Bold",
            "evs": {"hp": 252, "spe":252 , "spd": 4},
            "teraType": ["Fairy"],
            "ability": ["Intimidate","Shadow Tag"]
        },
        {
            "species": "Mandelman",
            "weight": 20,
            "moves": [
                ["Nasty Plot"],
                ["Destiny Bond"],
                ["Disable","Parting Shot"],
                ["Baddy Bad"]
            ],
            "item": ["Light Clay"],
            "nature": "Bold",
            "evs": {"hp": 252, "def":252 , "spd": 4},
            "teraType": ["Fairy"],
            "ability": ["Intimidate","Shadow Tag"]
        },
        {
            "species": "Mandelman",
            "weight": 20,
            "moves": [
                ["Lovely Kiss"],
                ["Brick Break"],
                ["Knock Off","Pursuit"],
                ["Baddy Bad"]
            ],
            "item": ["Light Clay","Focus Sash"],
            "nature": "Bold",
            "evs": {"spa": 252, "spe":252 , "spd": 4},
            "teraType": ["Fairy"],
            "ability": ["Bad Dreams","Shadow Tag"]
        },
        {
            "species": "Mandelman",
            "weight": 5,
            "moves": [
                ["Night Shade"],
                ["Sucker Punch"],
                ["Destiny Bond"],
                ["Taunt"]
            ],
            "item": ["Focus Sash"],
            "nature": "Timid",
            "evs": {"hp": 252, "spe":252 , "spd": 4},
            "teraType": ["Fairy"],
            "ability": ["Shadow Tag"]
        }
      ]
    },
    "achaethena": {
      "weight": 50,
      "sets": [
        {
            "species": "Achaethena",
            "weight": 20,
            "moves": [
                ["Close Combat", "Superpower","Drain Punch"],
                ["Mach Punch"],
                ["Poison Jab", "Taunt", "Strength Sap", "Spirit Break", "Leech Life","Ice Punch"],
                ["Knock Off", "Pursuit", "Succuby Kiss" ]
            ],
            "item": ["Focus Sash", "Life Orb", "Expert Belt"],
            "nature": "Jolly",
            "evs": {"spe": 252, "atk": 252 , "spd": 4 },
            "teraType": ["Fairy"],
            "ability": ["Vampire", "Levitate", "Merciless"]
        },
        {
            "species": "Achaethena",
            "weight": 20,
            "moves": [
                ["Close Combat", "Superpower","Drain Punch"],
                ["Mach Punch"],
                ["Poison Jab", "Taunt"],
                ["Knock Off", "Pursuit", "Succuby Kiss" ]
            ],
            "item": ["Focus Sash", "Life Orb", "Expert Belt"],
            "nature": "Adamant",
            "evs": {"spe": 252, "atk": 252 , "spd": 4 },
            "teraType": ["Fairy"],
            "ability": ["Vampire", "Levitate", "Merciless"]
        },
        {
            "species": "Achaethena",
            "weight": 5,
            "moves": [
                ["Calm Mind", "Nasty Plot"],
                ["Draining Kiss", "Alluring Voice", "Soul Blast"],
                ["Aura Sphere", "Vacuum Wave"],
                ["Dark Pulse"]
            ],
            "item": ["Focus Sash", "Life Orb", "Expert Belt"],
            "nature": "Modest",
            "evs": { "spa": 252 , "spe": 252, "spd": 4},
            "teraType": ["Fairy"],
            "ability": ["Levitate", "Vampire"]
        },
        {
            "species": "Achaethena",
            "weight": 20,
            "moves": [
                ["Close Combat", "Superpower","Drain Punch"],
                ["Mach Punch"],
                ["Poison Jab","Parting Shot"],
                ["Knock Off", "Pursuit", "Succuby Kiss" ]
            ],
            "item": ["Choice Scarf"],
            "nature": "Jolly",
            "evs": {"spe": 252, "atk": 252 , "spd": 4 },
            "teraType": ["Fairy"],
            "ability": ["Vampire", "Levitate"]
        }
      ]
    },
    "hierocculte": {
      "weight": 50,
      "sets": [
        {
            "species": "Hierocculte",
            "weight": 20,
            "moves": [
                ["Earth Power"],
                ["Stealth Rock","Spikes"],
                ["Light Screen","Reflect","Hypnosis","Will-O-Wisp","Trick Room"],
                ["Teleport" ]
            ],
            "item": ["Rocky Helmet"],
            "nature": "Calm",
            "evs": {"hp": 252, "def": 252 , "spd": 4 },
            "teraType": ["Fairy"],
            "ability": ["Gravity Falls"]
        }
      ]
    },
    "mossemeros": {
      "weight": 50,
      "sets": [
        {
            "species": "Mossemeros",
            "weight": 20,
            "moves": [
                ["Spikes"],
                ["Earthquake","Bonemerang"],
                ["Rapid Spin"],
                ["Explosion"]
            ],
            "item": ["Rocky Helmet"],
            "nature": "Careful",
            "evs": {"hp": 252, "spd": 252 , "def": 4 },
            "teraType": ["Fairy"],
            "ability": ["Fragmentate"]
        },
        {
            "species": "Mossemeros",
            "weight": 20,
            "moves": [
                ["Body Press"],
                ["Rapid Spin"],
                ["Poltergeist","Shadowbone"],
                ["Stone Edge"]
            ],
            "item": ["Rocky Helmet"],
            "nature": "Adamant",
            "evs": {"hp": 252, "atk": 252 , "def": 4 },
            "teraType": ["Fairy"],
            "ability": ["Fragmentate"]
        },
        {
            "species": "Mossemeros",
            "weight": 20,
            "moves": [
                ["Shadow Sneak"],
                ["Earthquake","Bonemerang"],
                ["Shell Smash"],
                ["Stone Edge","Head Smash"]
            ],
            "item": ["White Herb"],
            "nature": "Adamant",
            "evs": {"hp": 252, "atk": 252 , "def": 4 },
            "teraType": ["Fairy"],
            "ability": ["Fragmentate"]
        },
        {
            "species": "Mossemeros",
            "weight": 5,
            "moves": [
                ["Substitute"],
                ["Last Respects"],
                ["Rapid Spin"],
                ["Stone Edge"]
            ],
            "item": ["Rocky Helmet"],
            "nature": "Adamant",
            "evs": {"hp": 252, "spd": 252 , "atk": 4 },
            "teraType": ["Fairy"],
            "ability": ["Fragmentate"]
        }
      ]
    },
    "auberjaw": {
      "weight": 80,
      "sets": [
        {
            "species": "Auberjaw",
            "weight": 20,
            "moves": [
                ["Snap Trap"],
                ["Leech Seed"],
                ["Protect"],
                ["Substitute","Body Press"]
            ],
            "item": ["Leftovers","Sitrus Berry","Yache Berry"],
            "nature": "Impish",
            "evs": {"hp": 252, "def": 252 , "atk": 4 },
            "teraType": ["Fairy"],
            "ability": ["Strong Jaw","Harvest"]
        },
        {
            "species": "Auberjaw",
            "weight": 20,
            "moves": [
                ["Snap Trap"],
                ["Leech Seed"],
                ["Protect"],
                ["Substitute"]
            ],
            "item": ["Leftovers","Sitrus Berry","Yache Berry"],
            "nature": "Impish",
            "evs": {"hp": 252, "def": 252 , "atk": 4 },
            "teraType": ["Fairy"],
            "ability": ["Strong Jaw","Harvest"]
        },
        {
            "species": "Auberjaw",
            "weight": 5,
            "moves": [
                ["Power Whip"],
                ["Earthquake"],
                ["Body Press"],
                ["Ice Fang"]
            ],
            "item": ["Assault Vest"],
            "nature": "Adamant",
            "evs": {"hp": 252, "atk": 252 , "def": 4 },
            "teraType": ["Fairy"],
            "ability": ["Strong Jaw","Harvest"]
        }
      ]
    },
    "daemonix": {
      "weight": 25,
      "sets": [
        {
            "species": "Daemonix",
            "weight": 20,
            "moves": [
                ["Calm Mind"],
                ["Strength Sap","Moonlight"],
                ["Draining Kiss"],
                ["Substitute","Taunt","Charm","Encore"]
            ],
            "item": ["Eviolite","Leftovers"],
            "nature": "Timid",
            "evs": {"spa": 252, "spe": 252 , "def": 4 },
            "teraType": ["Fairy"],
            "ability": ["Prankster"]
        }
      ]
    },
    "phantasm": {
      "weight": 50,
      "sets": [
        {
            "species": "Phantasm",
            "weight": 20,
            "moves": [
                ["Protect"],
                ["Knock Off"],
                ["Iron Defense"],
                ["Body Press"]
            ],
            "item": ["Leftovers"],
            "nature": "Careful",
            "evs": {"hp": 252, "spd": 252 , "def": 4 },
            "teraType": ["Fairy"],
            "ability": ["Stamina"]
        },
        {
            "species": "Phantasm",
            "weight": 20,
            "moves": [
                ["Protect","Pain Split"],
                ["Knock Off"],
                ["Explosion"],
                ["Bondage"]
            ],
            "item": ["Wide Lens"],
            "nature": "Adamant",
            "evs": {"atk": 252, "hp": 252 , "def": 4 },
            "teraType": ["Fairy"],
            "ability": ["Laceration"]
        },
        {
            "species": "Phantasm",
            "weight": 20,
            "moves": [
                ["Protect"],
                ["Knock Off"],
                ["Explosion"],
                ["Bondage"]
            ],
            "item": ["Binding Band"],
            "nature": "Adamant",
            "evs": {"atk": 252, "hp": 252 , "def": 4 },
            "teraType": ["Fairy"],
            "ability": ["Stamina"]
        },
        {
            "species": "Phantasm",
            "weight": 5,
            "moves": [
                ["Mean Look"],
                ["Rest"],
                ["Captivate"],
                ["Spite"]
            ],
            "item": ["Leftovers"],
            "nature": "Bold",
            "evs": {"hp": 252, "def": 252 , "spd": 4 },
            "teraType": ["Fairy"],
            "ability": ["Stamina"]
        }
      ]
    },
    "beelzeros": {
      "weight": 50,
      "sets": [
        {
            "species": "Beelzeros",
            "weight": 20,
            "moves": [
                ["Knock Off"],
                ["Swords Dance","Bulk Up"],
                ["Drain Punch"],
                ["Sucker Punch","Pursuit"]
            ],
            "item": ["Black Glasses","Expert Belt","Life Orb","Lum Berry"],
            "nature": "Adamant",
            "evs": {"spa": 252, "spe": 252 , "def": 4 },
            "teraType": ["Fairy"],
            "ability": ["Vampire"]
        },
        {
            "species": "Beelzeros",
            "weight": 20,
            "moves": [
                ["Knock Off"],
                ["Sucker Punch"],
                ["Drain Punch"],
                ["Pursuit"]
            ],
            "item": ["Assault Vest"],
            "nature": "Adamant",
            "evs": {"spa": 252, "spe": 252 , "def": 4 },
            "teraType": ["Fairy"],
            "ability": ["Vampire"]
        },
        {
            "species": "Beelzeros",
            "weight": 5,
            "moves": [
                ["Ceaseless Edge"],
                ["Taunt"],
                ["Lovely Kiss"],
                ["Pursuit"]
            ],
            "item": ["Mental Herb"],
            "nature": "Adamant",
            "evs": {"spe": 252, "hp": 252 , "def": 4 },
            "teraType": ["Fairy"],
            "ability": ["Insomnia"]
        }
      ]
    },
    "pythagon": {
      "weight": 70,
      "sets": [
        {
            "species": "Pythagon",
            "weight": 20,
            "moves": [
                ["Fickle Beam"],
                ["Substitute"],
                ["Agility"],
                ["Focus Blast"]
            ],
            "item": ["Life Orb","Expert Belt"],
            "nature": "Timid",
            "evs": {"spa": 252, "spe": 252 , "def": 4 },
            "teraType": ["Fairy"],
            "ability": ["Simple"]
        },
        {
            "species": "Pythagon",
            "weight": 20,
            "moves": [
                ["Fickle Beam"],
                ["Fire Blast","Thunder"],
                ["Volt Switch"],
                ["Focus Blast"]
            ],
            "item": ["Choice Scarf"],
            "nature": "Timid",
            "evs": {"spa": 252, "spe": 252 , "def": 4 },
            "teraType": ["Fairy"],
            "ability": ["Download"]
        },
        {
            "species": "Pythagon",
            "weight": 20,
            "moves": [
                ["Fickle Beam"],
                ["Agility"],
                ["Calm Mind"],
                ["Focus Blast"]
            ],
            "item": ["Life Orb","Expert Belt"],
            "nature": "Modest",
            "evs": {"spa": 252, "spe": 252 , "def": 4 },
            "teraType": ["Fairy"],
            "ability": ["Simple"]
        }
      ]
    },
    "parademise": {
      "weight": 50,
      "sets": [
        {
            "species": "Parademise",
            "weight": 20,
            "moves": [
                ["Flash Cannon"],
                ["Focus Blast","Aura Sphere"],
                ["Dark Pulse"],
                ["Volt Switch"]
            ],
            "item": ["Choice Scarf"],
            "nature": "Timid",
            "evs": {"spa": 252, "spe": 252 , "def": 4 },
            "teraType": ["Fairy"],
            "ability": ["Mega Launcher"]
        },
        {
            "species": "Parademise",
            "weight": 20,
            "moves": [
                ["Wish"],
                ["Dark Pulse"],
                ["Doom Desire"],
                ["Protect"]
            ],
            "item": ["Leftovers"],
            "nature": "Bold",
            "evs": {"hp": 252, "def": 252 , "spd": 4 },
            "teraType": ["Fairy"],
            "ability": ["Levitate"]
        },
        {
            "species": "Parademise",
            "weight": 20,
            "moves": [
                ["Flash Cannon"],
                ["Focus Blast"],
                ["Volt Switch"],
                ["Tailwind"]
            ],
            "item": ["Focus Sash"],
            "nature": "Modest",
            "evs": {"hp": 252, "spa": 252 , "spd": 4 },
            "teraType": ["Fairy"],
            "ability": ["Mega Launcher"]
        }
      ]
    },
    "stalibri": {
      "weight": 25,
      "sets": [
          {
              "species": "Stalibri",
              "weight": 20,
              "moves": [
                  ["Stealth Rock"],
                  ["Drill Run"],
                  ["Taunt"],
                  ["Thief"]
              ],
              "item": ["Focus Sash"],
              "nature": "Jolly",
              "evs": {"atk": 252, "spe": 252, "spd": 4},
              "teraType": ["Grass", "Poison", "Water"],
              "ability": ["Inner Focus"]
          }
      ]
    },
    "zardopium": {
      "weight": 50,
      "sets": [
          {
              "species": "Zardopium",
              "weight": 20,
              "moves": [
                  ["Stone Edge"],
                  ["Drill Run"],
                  ["Substitute"],
                  ["Rock Polish"]
              ],
              "item": ["Sitrus Berry","Leftovers"],
              "nature": "Adament",
              "evs": {"atk": 252, "spe": 252, "spd": 4},
              "teraType": ["Grass", "Poison", "Water"],
              "ability": ["Fur Coat"]
          },
          {
              "species": "Zardopium",
              "weight": 20,
              "moves": [
                  ["Stone Edge","Beak Blast"],
                  ["Stealth Rock"],
                  ["Whirlwind"],
                  ["Roost"]
              ],
              "item": ["Rocky Helmet","Heavy-Duty Boots"],
              "nature": "Careful",
              "evs": {"hp": 252, "spd": 252, "spe": 4},
              "teraType": ["Grass", "Poison", "Water"],
              "ability": ["Fur Coat"]
          },
          {
              "species": "Zardopium",
              "weight": 20,
              "moves": [
                  ["Beak Blast"],
                  ["Chilly Reception"],
                  ["Defog"],
                  ["Roost"]
              ],
              "item": ["Heavy-Duty Boots"],
              "nature": "Careful",
              "evs": {"hp": 252, "spd": 252, "spe": 4},
              "teraType": ["Grass", "Poison", "Water"],
              "ability": ["Fur Coat"]
          },
          {
              "species": "Zardopium",
              "weight": 5,
              "moves": [
                  ["Beak Blast"],
                  ["Stone Edge"],
                  ["Drill Run"],
                  ["Accelerock"]
              ],
              "item": ["Assault Vest"],
              "nature": "Adament",
              "evs": {"hp": 252, "atk": 252, "spe": 4},
              "teraType": ["Grass", "Poison", "Water"],
              "ability": ["Fur Coat"]
          }
      ]
    },
    "veuvoile": {
      "weight": 50,
      "sets": [
        {
              "species": "Veuvoile",
              "weight": 20,
              "moves": [
                  ["Sticky Web"],
                  ["Taunt"],
                  ["Knock Off"],
                  ["U-Turn"]
              ],
              "item": ["Black Sludge"],
              "nature": "Jolly",
              "evs": {"hp": 252, "spe": 252, "atk": 4},
              "teraType": ["Grass", "Poison", "Water"],
              "ability": ["Aroma Veil"]
          },
          {
              "species": "Veuvoile",
              "weight": 20,
              "moves": [
                  ["Toxic"],
                  ["Taunt"],
                  ["Knock Off"],
                  ["Aromatherapy"]
              ],
              "item": ["Black Sludge"],
              "nature": "Impish",
              "evs": {"hp": 252, "spe": 4, "spd": 252},
              "teraType": ["Grass", "Poison", "Water"],
              "ability": ["Pressure"]
          }
      ]
    },
    "palmypince": {
      "weight": 50,
      "sets": [
        {
            "species": "Palmypince",
            "weight": 20,
            "moves": [
                ["Stone Edge"],
                ["Stealth Rock"],
                ["Flip Turn"],
                ["Milk Drink"]
            ],
            "item": ["Heavy-Duty Boots"],
            "nature": "Impish",
            "evs": {"hp": 252, "spd": 252 , "atk": 4 },
            "teraType": ["Fairy"],
            "ability": ["Pickup"]
        },
        {
            "species": "Palmypince",
            "weight": 20,
            "moves": [
                ["Stone Edge","Head Smash"],
                ["Seed Bomb","Wood Hammer"],
                ["Earthquake","Cross Chop"],
                ["Shell Smash"]
            ],
            "item": ["White Herb"],
            "nature": "Adament",
            "evs": {"atk": 252, "spe": 252 , "def": 4 },
            "teraType": ["Fairy"],
            "ability": ["Pickup"]
        },
        {
            "species": "Palmypince",
            "weight": 20,
            "moves": [
                ["Rock Blast"],
                ["Stealth Rock"],
                ["Leech Seed"],
                ["Milk Drink"]
            ],
            "item": ["Leftovers","Rocky Helmet"],
            "nature": "Impish",
            "evs": {"hp": 252, "spd": 252 , "atk": 4 },
            "teraType": ["Fairy"],
            "ability": ["Pickup"]
        },
        {
            "species": "Palmypince",
            "weight": 5,
            "moves": [
                ["Solar Blade"],
                ["Head Smash"],
                ["Earthquake"],
                ["Swords Dance"]
            ],
            "item": ["Life Orb"],
            "nature": "Adamant",
            "evs": {"hp": 252, "spd": 252 , "atk": 4 },
            "teraType": ["Fairy"],
            "ability": ["Chlorophyll"]
        }
      ]
    },
    "tundragon": {
      "weight": 70,
      "sets": [
        {
            "species": "Tundragon",
            "weight": 20,
            "moves": [
                ["Icicle Spear"],
                ["Slack Off"],
                ["Cotton Guard"],
                ["Body Press"]
            ],
            "item": ["Loaded Dice"],
            "nature": "Impish",
            "evs": {"hp": 252, "spd": 252 , "atk": 4 },
            "teraType": ["Fairy"],
            "ability": ["Fluffy"]
        },
        {
            "species": "Tundragon",
            "weight": 20,
            "moves": [
                ["Icicle Spear"],
                ["Scale Shot"],
                ["Bulldoze"],
                ["Chilly Reception"]
            ],
            "item": ["Choice Scarf"],
            "nature": "Jolly",
            "evs": {"spe": 252, "atk": 252 , "spd": 4 },
            "teraType": ["Fairy"],
            "ability": ["Skill Link"]
        },
        {
            "species": "Tundragon",
            "weight": 10,
            "moves": [
                ["Triple Axel"],
                ["Slack Off"],
                ["Haze"],
                ["Engelure"]
            ],
            "item": ["Leftovers"],
            "nature": "Jolly",
            "evs": {"spe": 252, "hp": 252 , "atk": 4 },
            "teraType": ["Fairy"],
            "ability": ["Fluffy"]
        },
        {
            "species": "Tundragon",
            "weight": 5,
            "moves": [
                ["Triple Axel"],
                ["Bulldoze"],
                ["Ice Shard"],
                ["Dragon Tail"]
            ],
            "item": ["Assault Vest"],
            "nature": "Jolly",
            "evs": {"spe": 252, "spd": 4 , "atk": 252 },
            "teraType": ["Fairy"],
            "ability": ["Fluffy"]
        }
      ]
    },
    "rottenia": {
      "weight": 80,
      "sets": [
        {
            "species": "Rottenia",
            "weight": 20,
            "moves": [
                ["Protect"],
                ["Toxic"],
                ["Infestation"],
                ["Foul Play","Destiny Bond"]
            ],
            "item": ["Leftovers"],
            "nature": "Sassy",
            "evs": {"hp": 252, "spd": 252 , "def": 4 },
            "teraType": ["Fairy"],
            "ability": ["Infiltrator"]
        }
      ]
    },
    "rochiere": {
      "weight": 100,
      "sets": [
        {
            "species": "Rochie\u0300re",
            "weight": 20,
            "moves": [
                ["Recover"],
                ["Revival Blessing"],
                ["Aromatherapy"],
                ["Strange Steam"]
            ],
            "item": ["Leppa Berry"],
            "nature": "Calm",
            "evs": {"hp": 248, "spd": 252 , "def": 8 },
            "teraType": ["Fairy"],
            "ability": ["Misty Surge"]
        }
      ]
    },
    "wardelith": {
      "weight": 50,
      "sets": [
        {
            "species": "Wardelith",
            "weight": 20,
            "moves": [
                ["Meteor Beam"],
                ["Earth Power"],
                ["Stealth Rock"],
                ["Power Gem"]
            ],
            "item": ["Power Herb"],
            "nature": "Modest",
            "evs": {"hp": 252, "spa": 252 , "def": 4 },
            "teraType": ["Fairy"],
            "ability": ["Sturdy","Rough Skin"]
        },
        {
            "species": "Wardelith",
            "weight": 5,
            "moves": [
                ["Fire Blast"],
                ["Block"],
                ["Perish Song"],
                ["Protect"]
            ],
            "item": ["Leftovers"],
            "nature": "Calm",
            "evs": {"hp": 252, "spd": 252 , "def": 4 },
            "teraType": ["Fairy"],
            "ability": ["Rough Skin"]
        },
        {
            "species": "Wardelith",
            "weight": 20,
            "moves": [
                ["Meteor Beam"],
                ["Earth Power"],
                ["Knock Off"],
                ["Sandstorm"]
            ],
            "item": ["Smooth Rock"],
            "nature": "Quiet",
            "evs": {"hp": 252, "spa": 252 , "def": 4 },
            "teraType": ["Fairy"],
            "ability": ["Sturdy","Rough Skin"]
        },
        {
            "species": "Wardelith",
            "weight": 20,
            "moves": [
                ["Earth Power"],
                ["Power Gem"],
                ["Knock Off"],
                ["Explosion"]
            ],
            "item": ["Rocky Helmet"],
            "nature": "Quiet",
            "evs": {"hp": 252, "spa": 252 , "def": 4 },
            "teraType": ["Fairy"],
            "ability": ["Rough Skin"]
        }
      ]
    }
}
